scripts/debug_embedding.py
scripts/debug_full.py
scripts/debug_pg.py
scripts/investigate_timeout.py
scripts/test_embedding.py
scripts/validate_agents.py
scripts/validate_all_dbs.py
scripts/verify_deps.py
tests/test_databases.py
tests/test_hybrid_implementation.py
tests/test_optional_dependencies.py
tests/test_protocol_compliance.py
tests/test_pruning.py
tests/test_vector_mcp.py
vector_mcp/__init__.py
vector_mcp/__main__.py
vector_mcp/mcp_config.json
vector_mcp/middlewares.py
vector_mcp/utils.py
vector_mcp/vector_agent.py
vector_mcp/vector_mcp.py
vector_mcp/retriever/__init__.py
vector_mcp/retriever/chromadb_retriever.py
vector_mcp/retriever/couchbase_retriever.py
vector_mcp/retriever/llamaindex_retriever.py
vector_mcp/retriever/mongodb_retriever.py
vector_mcp/retriever/pgvector_retriever.py
vector_mcp/retriever/qdrant_retriever.py
vector_mcp/retriever/retriever.py
vector_mcp/skills/vector-mcp-collection-management/SKILL.md
vector_mcp/skills/vector-mcp-search/SKILL.md
vector_mcp/vectordb/__init__.py
vector_mcp/vectordb/base.py
vector_mcp/vectordb/chromadb.py
vector_mcp/vectordb/couchbase.py
vector_mcp/vectordb/mongodb.py
vector_mcp/vectordb/pgvector.py
vector_mcp/vectordb/qdrant.py
vector_mcp/vectordb/utils.py
vector_mcp-1.0.8.dist-info/licenses/LICENSE
vector_mcp-1.0.8.dist-info/METADATA
vector_mcp-1.0.8.dist-info/WHEEL
vector_mcp-1.0.8.dist-info/entry_points.txt
vector_mcp-1.0.8.dist-info/top_level.txt
vector_mcp-1.0.8.dist-info/RECORD
