Metadata-Version: 2.4
Name: vector-mcp
Version: 1.0.8
Summary: Integrate RAG into AI Agents via MCP Server. Supports multiple Vector database technologies.
Author-email: Audel Rouhi <knucklessg1@gmail.com>
Classifier: Development Status :: 5 - Production/Stable
Classifier: License :: Public Domain
Classifier: Environment :: Console
Classifier: Operating System :: POSIX :: Linux
Classifier: Programming Language :: Python :: 3
Requires-Python: >=3.10
License-File: LICENSE
Requires-Dist: fastmcp>=3.0.0b1
Requires-Dist: markdownify>=1.2.2
Requires-Dist: beautifulsoup4>=4.14.3
Requires-Dist: ebooklib>=0.19
Requires-Dist: html2text>=2025.4.15
Requires-Dist: ipython>=9.9.0
Requires-Dist: pypdf>=6.6.2
Requires-Dist: protobuf>=6.33.4
Requires-Dist: llama-index-core>=0.14.13
Requires-Dist: llama-index-llms-langchain>=0.7.1
Requires-Dist: llama-index-vector-stores-chroma>=0.5.5
Requires-Dist: chromadb>=1.4.1
Requires-Dist: llama-index-readers-file>=0.2.0
Requires-Dist: eunomia-mcp>=0.3.10
Provides-Extra: pgvector
Requires-Dist: pgvector>=0.4.2; extra == "pgvector"
Requires-Dist: psycopg>=3.3.2; extra == "pgvector"
Requires-Dist: llama-index-vector-stores-postgres>=0.7.3; extra == "pgvector"
Provides-Extra: chromadb
Requires-Dist: chromadb>=1.4.1; extra == "chromadb"
Requires-Dist: llama-index-vector-stores-chroma>=0.5.5; extra == "chromadb"
Provides-Extra: couchbase
Requires-Dist: couchbase>=4.5.0; extra == "couchbase"
Requires-Dist: llama-index-vector-stores-couchbase>=0.6.0; extra == "couchbase"
Provides-Extra: qdrant
Requires-Dist: qdrant-client>=1.16.2; extra == "qdrant"
Requires-Dist: fastembed>=0.7.4; extra == "qdrant"
Requires-Dist: llama-index-vector-stores-qdrant>=0.9.1; extra == "qdrant"
Provides-Extra: mongodb
Requires-Dist: pymongo>=4.16.0; extra == "mongodb"
Requires-Dist: llama-index-vector-stores-mongodb>=0.9.1; extra == "mongodb"
Provides-Extra: huggingface
Requires-Dist: llama-index-embeddings-huggingface>=0.6.1; extra == "huggingface"
Requires-Dist: sentence_transformers>=5.2.2; extra == "huggingface"
Provides-Extra: a2a
Requires-Dist: pydantic-ai-slim[a2a,ag-ui,anthropic,fastmcp,google,huggingface,openai,web]>=1.48.0; extra == "a2a"
Requires-Dist: pydantic-ai-skills>=0.4.0; extra == "a2a"
Requires-Dist: fastapi>=0.128.0; extra == "a2a"
Provides-Extra: all
Requires-Dist: fastmcp>=3.0.0b1; extra == "all"
Requires-Dist: sentence_transformers>=5.2.2; extra == "all"
Requires-Dist: markdownify>=1.2.2; extra == "all"
Requires-Dist: beautifulsoup4>=4.14.3; extra == "all"
Requires-Dist: ebooklib>=0.19; extra == "all"
Requires-Dist: html2text>=2025.4.15; extra == "all"
Requires-Dist: ipython>=9.9.0; extra == "all"
Requires-Dist: pypdf>=6.6.2; extra == "all"
Requires-Dist: protobuf>=6.33.4; extra == "all"
Requires-Dist: llama-index-core>=0.14.13; extra == "all"
Requires-Dist: llama-index-llms-langchain>=0.7.1; extra == "all"
Requires-Dist: llama-index-embeddings-huggingface>=0.6.1; extra == "all"
Requires-Dist: llama-index-vector-stores-mongodb>=0.9.1; extra == "all"
Requires-Dist: llama-index-vector-stores-qdrant>=0.9.1; extra == "all"
Requires-Dist: llama-index-vector-stores-couchbase>=0.6.0; extra == "all"
Requires-Dist: llama-index-vector-stores-chroma>=0.5.5; extra == "all"
Requires-Dist: llama-index-vector-stores-postgres>=0.7.3; extra == "all"
Requires-Dist: pgvector>=0.4.2; extra == "all"
Requires-Dist: psycopg>=3.3.2; extra == "all"
Requires-Dist: chromadb>=1.4.1; extra == "all"
Requires-Dist: couchbase>=4.5.0; extra == "all"
Requires-Dist: qdrant-client>=1.16.2; extra == "all"
Requires-Dist: fastembed>=0.7.4; extra == "all"
Requires-Dist: pymongo>=4.16.0; extra == "all"
Requires-Dist: pydantic-ai-slim[a2a,ag-ui,anthropic,fastmcp,google,huggingface,openai,web]>=1.48.0; extra == "all"
Requires-Dist: pydantic-ai-skills>=0.4.0; extra == "all"
Requires-Dist: fastapi>=0.128.0; extra == "all"
Dynamic: license-file
